[
    {
        "name": "N/A",
        "value": "N/A"
    },
    {
        "name": "Shift-A",
        "value": "Shift-A"
    },
    {
        "name": "Shift-B",
        "value": "Shift-B"
    },
    {
        "name": "Shift-C",
        "value": "Shift-C"
    },
    {
        "name": "Shift-D",
        "value": "Shift-D"
    },
    {
        "name": "Shift-E",
        "value": "Shift-E"
    },
    {
        "name": "Shift-1",
        "value": "Shift-1"
    },
    {
        "name": "Shift-2",
        "value": "Shift-2"
    },
    {
        "name": "Shift-3",
        "value": "Shift-3"
    },
    {
        "name": "Shift-4",
        "value": "Shift-4"
    },
    {
        "name": "Shift-5",
        "value": "Shift-5"
    }
]
